shvcli/__init__.py
shvcli/__main__.py
shvcli/__version__.py
shvcli/afterconn.py
shvcli/args.py
shvcli/builtin.py
shvcli/cli.py
shvcli/client.py
shvcli/cliitems.py
shvcli/complet.py
shvcli/config.py
shvcli/file.py
shvcli/lsdir.py
shvcli/oauth.py
shvcli/option.py
shvcli/options.py
shvcli/plugins.py
shvcli/py.typed
shvcli/scan.py
shvcli/state.py
shvcli/tree.py
shvcli/url.py
shvcli/valid.py
shvcli/builtins/__init__.py
shvcli/builtins/broker.py
shvcli/builtins/cd.py
shvcli/builtins/file.py
shvcli/builtins/help.py
shvcli/builtins/history.py
shvcli/builtins/scan.py
shvcli/builtins/set.py
shvcli/builtins/tree.py
shvcli/tools/__init__.py
shvcli/tools/complet.py
shvcli/tools/print.py
shvcli-0.8.0.dist-info/licenses/LICENSE
shvcli-0.8.0.dist-info/METADATA
shvcli-0.8.0.dist-info/WHEEL
shvcli-0.8.0.dist-info/entry_points.txt
shvcli-0.8.0.dist-info/top_level.txt
shvcli-0.8.0.dist-info/RECORD
