Metadata-Version: 2.4
Name: shvcli
Version: 0.8.0
Summary: Silicon Heaven CLI access application
Author: Elektroline a.s.
License: MIT License
Project-URL: repository, https://gitlab.com/silicon-heaven/shvcli
Classifier: Development Status :: 4 - Beta
Classifier: Operating System :: OS Independent
Classifier: Environment :: Console
Classifier: Intended Audience :: End Users/Desktop
Classifier: Topic :: Home Automation
Classifier: Topic :: System :: Shells
Classifier: Topic :: Terminals
Requires-Python: >=3.11
License-File: LICENSE
Requires-Dist: pyshv>=0.10.0
Requires-Dist: prompt_toolkit
Requires-Dist: pygments
Requires-Dist: pyxdg
Requires-Dist: more-itertools
Dynamic: license-file
